pyhexwatershed/__init__.py
pyhexwatershed/algorithms/__init__.py
pyhexwatershed/algorithms/auxiliary/__init__.py
pyhexwatershed/algorithms/auxiliary/export_json_to_geojson_polygon.py
pyhexwatershed/algorithms/auxiliary/export_json_to_geojson_polyline.py
pyhexwatershed/algorithms/auxiliary/merge_cell_to_polygon.py
pyhexwatershed/algorithms/auxiliary/merge_stream_edge_to_stream_segment.py
pyhexwatershed/classes/__init__.py
pyhexwatershed/classes/_hpc.py
pyhexwatershed/classes/_visual.py
pyhexwatershed/classes/pycase.py
pyhexwatershed/configuration/__init__.py
pyhexwatershed/configuration/change_json_key_value.py
pyhexwatershed/configuration/create_template_configuration_file.py
pyhexwatershed/configuration/path_manager.py
pyhexwatershed/configuration/read_configuration_file.py
hexwatershed-0.2.30.dist-info/AUTHORS.rst
hexwatershed-0.2.30.dist-info/LICENSE.md
hexwatershed-0.2.30.dist-info/METADATA
hexwatershed-0.2.30.dist-info/WHEEL
hexwatershed-0.2.30.dist-info/top_level.txt
hexwatershed-0.2.30.dist-info/RECORD
