Metadata-Version: 2.1
Name: hexwatershed
Version: 0.2.30
Summary: A mesh-independent flow direction model for hydrologic models
Home-page: https://github.com/changliao1025/pyhexwatershed
Author: Chang Liao
Author-email: chang.liao@pnnl.gov
License: custom
Keywords: hexwatershed,hydrology,hydrologic modeling,hydrologic model,flow direction,hexagon
Platform: UNKNOWN
Classifier: Development Status :: 4 - Beta
Classifier: Operating System :: OS Independent
Classifier: Intended Audience :: Science/Research
Classifier: Programming Language :: Python
Classifier: Programming Language :: Python :: 3
Classifier: Programming Language :: C++
Classifier: Topic :: Scientific/Engineering
Classifier: Topic :: Scientific/Engineering :: Hydrology
Classifier: Topic :: Scientific/Engineering :: GIS
Classifier: Topic :: Scientific/Engineering :: Physics
Requires-Python: >=3.8.0
Requires-Dist: numpy
Requires-Dist: gdal
Requires-Dist: pyearth
Requires-Dist: pyflowline
Provides-Extra: visualization
Requires-Dist: cython ; extra == 'visualization'
Requires-Dist: matplotlib ; extra == 'visualization'
Requires-Dist: cartopy >=0.21.0 ; extra == 'visualization'
